Metadata-Version: 2.1
Name: actionflow
Version: 0.0.5
Summary: LLM agent workflows
Home-page: https://github.com/shibing624/actionflow
Author: XuMing
Author-email: xuming624@qq.com
License: Apache License 2.0
Keywords: actionflow,Agent Tool,action,agent
Platform: UNKNOWN
Classifier: Development Status :: 5 - Production/Stable
Classifier: Intended Audience :: Developers
Classifier: Intended Audience :: Education
Classifier: Intended Audience :: Science/Research
Classifier: License :: OSI Approved :: Apache Software License
Classifier: Operating System :: OS Independent
Classifier: Programming Language :: Python :: 3
Classifier: Topic :: Scientific/Engineering :: Artificial Intelligence
Requires-Python: >=3.8.0
License-File: LICENSE
